sklearn4x/__init__.py
sklearn4x/sklearn4x.py
sklearn4x/core/BaseSerializer.py
sklearn4x/core/BinaryBuffer.py
sklearn4x/core/BinaryPackage.py
sklearn4x/core/__init__.py
sklearn4x/core/file_versions/BinaryPackageV1.py
sklearn4x/core/file_versions/__init__.py
sklearn4x/serializers/__init__.py
sklearn4x/serializers/serializers_list.py
sklearn4x/serializers/naive_bayes/BernoulliNaiveBayesSerializer.py
sklearn4x/serializers/naive_bayes/CategoricalNaiveBayesSerializer.py
sklearn4x/serializers/naive_bayes/ComplementNaiveBayesSerializer.py
sklearn4x/serializers/naive_bayes/GaussianNaiveBayesSerializer.py
sklearn4x/serializers/naive_bayes/MultinomialNaiveBayesSerializer.py
sklearn4x/serializers/naive_bayes/__init__.py
sklearn4x/serializers/preprocessings/BinarizerSerializer.py
sklearn4x/serializers/preprocessings/KBinsDiscretizerSerializer.py
sklearn4x/serializers/preprocessings/LabelBinarizerSerializer.py
sklearn4x/serializers/preprocessings/LabelEncoderSerializer.py
sklearn4x/serializers/preprocessings/MaxAbsScalerSerializer.py
sklearn4x/serializers/preprocessings/MinMaxScalerSerializer.py
sklearn4x/serializers/preprocessings/MultiLabelBinarizerSerializer.py
sklearn4x/serializers/preprocessings/NormalizerSerializer.py
sklearn4x/serializers/preprocessings/OneHotEncoderSerializer.py
sklearn4x/serializers/preprocessings/OrdinalEncoderSerializer.py
sklearn4x/serializers/preprocessings/PolynomialFeaturesSerializer.py
sklearn4x/serializers/preprocessings/PowerTransformerSerializer.py
sklearn4x/serializers/preprocessings/QuantileTransformerSerializer.py
sklearn4x/serializers/preprocessings/RobustScalerSerializer.py
sklearn4x/serializers/preprocessings/SplineTransformerSerializer.py
sklearn4x/serializers/preprocessings/StandardScalerSerializer.py
sklearn4x/serializers/preprocessings/__init__.py
sklearn4x-0.0.4.dist-info/LICENSE
sklearn4x-0.0.4.dist-info/METADATA
sklearn4x-0.0.4.dist-info/WHEEL
sklearn4x-0.0.4.dist-info/top_level.txt
sklearn4x-0.0.4.dist-info/RECORD
