Metadata-Version: 2.1
Name: sklearn4x
Version: 0.0.4
Summary: Packages sklearn models into a binary archive to be used in other languages.
Author: Mohammad Ali Yektaie
Author-email: ma_yektaie@outlook.com
License: UNKNOWN
Keywords: python,sklearn,edge,machine learning,ML,AI,Artificial Intelligence,Java,C#
Platform: UNKNOWN
Classifier: Development Status :: 1 - Planning
Classifier: Intended Audience :: Developers
Classifier: Programming Language :: Python :: 3
Classifier: Operating System :: Unix
Classifier: Operating System :: MacOS :: MacOS X
Classifier: Operating System :: Microsoft :: Windows
License-File: LICENSE
Requires-Dist: scikit-learn
Requires-Dist: numpy
